{
  "taskRoute": {
    "waypoints": [
      {
        "lat": -27.19179979,
        "lng": 151.22929705
      },
      {
        "lat": -27.28794386,
        "lng": 151.12699956
      },
      {
        "lat": -26.96438014,
        "lng": 151.21102404
      },
      {
        "lat": -27.04150403,
        "lng": 151.07790085
      },
      {
        "lat": -27.15359971,
        "lng": 151.255582
      }
    ],
    "flipSum": [
      "88.803506 km",
      "74.101413 km",
      "37.293680 km",
      "21.558213 km"
    ],
    "distance": "88.803506 km",
    "legsSum": [
      "14.702094 km",
      "51.509826 km",
      "67.245293 km",
      "88.803506 km"
    ],
    "legs": [
      "14.702094 km",
      "36.807733 km",
      "15.735467 km",
      "21.558213 km"
    ]
  },
  "startRoute": {
    "waypoints": [
      {
        "lat": -27.19391773,
        "lng": 151.23201463
      },
      {
        "lat": -27.29476754,
        "lng": 151.13860146
      }
    ],
    "flipSum": [
      "14.507596 km"
    ],
    "distance": "14.507596 km",
    "legsSum": [
      "14.507596 km"
    ],
    "legs": [
      "14.507596 km"
    ]
  },
  "taskRouteSpeedSubset": {
    "waypoints": [
      {
        "lat": -27.19179979,
        "lng": 151.22929705
      },
      {
        "lat": -27.28794386,
        "lng": 151.12699956
      },
      {
        "lat": -26.96438014,
        "lng": 151.21102404
      },
      {
        "lat": -27.04150403,
        "lng": 151.07790085
      },
      {
        "lat": -27.15359971,
        "lng": 151.255582
      }
    ],
    "flipSum": [
      "88.803506 km",
      "74.101413 km",
      "37.293680 km",
      "21.558213 km"
    ],
    "distance": "88.803506 km",
    "legsSum": [
      "14.702094 km",
      "51.509826 km",
      "67.245293 km",
      "88.803506 km"
    ],
    "legs": [
      "14.702094 km",
      "36.807733 km",
      "15.735467 km",
      "21.558213 km"
    ]
  },
  "speedRoute": {
    "waypoints": [
      {
        "lat": -27.19179979,
        "lng": 151.22929705
      },
      {
        "lat": -27.28794386,
        "lng": 151.12699956
      },
      {
        "lat": -26.96438014,
        "lng": 151.21102404
      },
      {
        "lat": -27.04150403,
        "lng": 151.07790085
      },
      {
        "lat": -27.15359971,
        "lng": 151.255582
      }
    ],
    "flipSum": [
      "88.803506 km",
      "74.101413 km",
      "37.293680 km",
      "21.558213 km"
    ],
    "distance": "88.803506 km",
    "legsSum": [
      "14.702094 km",
      "51.509826 km",
      "67.245293 km",
      "88.803506 km"
    ],
    "legs": [
      "14.702094 km",
      "36.807733 km",
      "15.735467 km",
      "21.558213 km"
    ]
  },
  "stopRoute": {
    "waypoints": [
      {
        "lat": -27.19179979,
        "lng": 151.22929705
      },
      {
        "lat": -27.28794386,
        "lng": 151.12699956
      },
      {
        "lat": -26.96438014,
        "lng": 151.21102404
      },
      {
        "lat": -27.04150403,
        "lng": 151.07790085
      },
      {
        "lat": -27.15359971,
        "lng": 151.255582
      }
    ],
    "flipSum": [
      "88.803506 km",
      "74.101413 km",
      "37.293680 km",
      "21.558213 km"
    ],
    "distance": "88.803506 km",
    "legsSum": [
      "14.702094 km",
      "51.509826 km",
      "67.245293 km",
      "88.803506 km"
    ],
    "legs": [
      "14.702094 km",
      "36.807733 km",
      "15.735467 km",
      "21.558213 km"
    ]
  }
}
