[
  [
    [
      "2",
      "Tony Armstrong"
    ],
    {
      "reach": "114.375112 km",
      "frac": 1
    }
  ],
  [
    [
      "22",
      "Steve Blenkinsop"
    ],
    {
      "reach": "114.375112 km",
      "frac": 1
    }
  ],
  [
    [
      "29",
      "Guy Hubbard"
    ],
    {
      "reach": "114.375112 km",
      "frac": 1
    }
  ],
  [
    [
      "5",
      "Jonny Durand"
    ],
    {
      "reach": "114.375112 km",
      "frac": 1
    }
  ],
  [
    [
      "12",
      "Rory Duncan"
    ],
    {
      "reach": "114.375112 km",
      "frac": 1
    }
  ],
  [
    [
      "46",
      "Harrison Rowntree"
    ],
    {
      "reach": "114.375112 km",
      "frac": 1
    }
  ],
  [
    [
      "20",
      "Konrad Heilmann"
    ],
    {
      "reach": "114.375112 km",
      "frac": 1
    }
  ],
  [
    [
      "44",
      "Josh Woods"
    ],
    {
      "reach": "114.375112 km",
      "frac": 1
    }
  ],
  [
    [
      "26",
      "Jason Kath"
    ],
    {
      "reach": "114.375112 km",
      "frac": 1
    }
  ],
  [
    [
      "4",
      "Nick Purcell"
    ],
    {
      "reach": "114.375112 km",
      "frac": 1
    }
  ],
  [
    [
      "33",
      "Niki Longshore"
    ],
    {
      "reach": "114.375112 km",
      "frac": 1
    }
  ],
  [
    [
      "19",
      "Scott Barrett"
    ],
    {
      "reach": "114.375112 km",
      "frac": 1
    }
  ],
  [
    [
      "13",
      "Matthew Barlow"
    ],
    {
      "reach": "114.375112 km",
      "frac": 1
    }
  ],
  [
    [
      "25",
      "Hagen Bruggemann"
    ],
    {
      "reach": "114.375112 km",
      "frac": 1
    }
  ],
  [
    [
      "8",
      "Rod Flockhart"
    ],
    {
      "reach": "114.375112 km",
      "frac": 1
    }
  ],
  [
    [
      "36",
      "Brad Porter"
    ],
    {
      "reach": "108.024112 km",
      "frac": 0.94447219
    }
  ],
  [
    [
      "39",
      "rob degroot"
    ],
    {
      "reach": "105.782112 km",
      "frac": 0.92487002
    }
  ],
  [
    [
      "42",
      "Mikhail Karmazin"
    ],
    {
      "reach": "102.417112 km",
      "frac": 0.89544928
    }
  ],
  [
    [
      "16",
      "Andrew Barnes"
    ],
    {
      "reach": "100.152112 km",
      "frac": 0.87564602
    }
  ],
  [
    [
      "10",
      "Craig Taylor"
    ],
    {
      "reach": "99.740112 km",
      "frac": 0.87204384
    }
  ],
  [
    [
      "24",
      "Brodrick Osborne"
    ],
    {
      "reach": "99.010112 km",
      "frac": 0.86566133
    }
  ],
  [
    [
      "7",
      "James Atkinson"
    ],
    {
      "reach": "98.706112 km",
      "frac": 0.86300341
    }
  ],
  [
    [
      "45",
      "steve crosby"
    ],
    {
      "reach": "94.224112 km",
      "frac": 0.82381657
    }
  ],
  [
    [
      "6",
      "Viv Clements"
    ],
    {
      "reach": "91.528112 km",
      "frac": 0.800245
    }
  ],
  [
    [
      "38",
      "Dave Stevens"
    ],
    {
      "reach": "87.531112 km",
      "frac": 0.76529859
    }
  ],
  [
    [
      "37",
      "John Spencer"
    ],
    {
      "reach": "87.512112 km",
      "frac": 0.76513247
    }
  ],
  [
    [
      "18",
      "Peter Adriaans"
    ],
    {
      "reach": "87.295112 km",
      "frac": 0.7632352
    }
  ],
  [
    [
      "51",
      "Billy Miller-Macleod"
    ],
    {
      "reach": "87.249112 km",
      "frac": 0.76283302
    }
  ],
  [
    [
      "35",
      "Anatoly Reyter"
    ],
    {
      "reach": "82.980112 km",
      "frac": 0.72550847
    }
  ],
  [
    [
      "23",
      "Noel Collins"
    ],
    {
      "reach": "80.784112 km",
      "frac": 0.70630848
    }
  ],
  [
    [
      "17",
      "Trevor Purcell"
    ],
    {
      "reach": "78.942112 km",
      "frac": 0.69020358
    }
  ],
  [
    [
      "43",
      "Simon West"
    ],
    {
      "reach": "65.138112 km",
      "frac": 0.56951299
    }
  ],
  [
    [
      "41",
      "Peter Burkitt"
    ],
    {
      "reach": "63.928112 km",
      "frac": 0.55893377
    }
  ],
  [
    [
      "14",
      "Tony Giammichele"
    ],
    {
      "reach": "63.011112 km",
      "frac": 0.55091629
    }
  ],
  [
    [
      "21",
      "Frank Chetcuti"
    ],
    {
      "reach": "62.762112 km",
      "frac": 0.54873924
    }
  ],
  [
    [
      "1",
      "Mark Alton"
    ],
    {
      "reach": "40.685112 km",
      "frac": 0.35571648
    }
  ],
  [
    [
      "32",
      "Rob Larkin"
    ],
    {
      "reach": "39.671112 km",
      "frac": 0.34685091
    }
  ],
  [
    [
      "9",
      "Rohan Taylor"
    ],
    {
      "reach": "36.320112 km",
      "frac": 0.31755258
    }
  ],
  [
    [
      "40",
      "Hossain Tefaili"
    ],
    {
      "reach": "29.805112 km",
      "frac": 0.26059089
    }
  ],
  [
    [
      "31",
      "Tomas Kellner"
    ],
    {
      "reach": "24.397112 km",
      "frac": 0.21330787
    }
  ],
  [
    [
      "48",
      "Derek Mckee"
    ],
    {
      "reach": "20.534112 km",
      "frac": 0.17953304
    }
  ],
  [
    [
      "27",
      "Guy Williams"
    ],
    {
      "reach": "17.592112 km",
      "frac": 0.15381066
    }
  ],
  [
    [
      "15",
      "Andrew Sharpe"
    ],
    {
      "reach": "10.820112 km",
      "frac": 0.09460198
    }
  ],
  [
    [
      "28",
      "John Harriot"
    ],
    {
      "reach": "10.253112 km",
      "frac": 0.08964461
    }
  ],
  [
    [
      "34",
      "dave moore"
    ],
    {
      "reach": "6.231112 km",
      "frac": 0.05447961
    }
  ]
]
